DateTimeTools/CDFEpoch.py
DateTimeTools/CDFEpochtoDate.py
DateTimeTools/ContUT.py
DateTimeTools/ContUTtoDate.py
DateTimeTools/DPlotLabel.py
DateTimeTools/DTPlotLabel.py
DateTimeTools/DateDifference.py
DateTimeTools/DateJoin.py
DateTimeTools/DateSplit.py
DateTimeTools/Datetime.py
DateTimeTools/DatetimetoDate.py
DateTimeTools/DayNo.py
DateTimeTools/DayNotoDate.py
DateTimeTools/DectoHHMM.py
DateTimeTools/Filter.py
DateTimeTools/HHMMtoDec.py
DateTimeTools/JulDay.py
DateTimeTools/JulDaytoDate.py
DateTimeTools/LeapYear.py
DateTimeTools/ListDates.py
DateTimeTools/MidTime.py
DateTimeTools/MinusDay.py
DateTimeTools/NearestTimeIndex.py
DateTimeTools/PlusDay.py
DateTimeTools/TimeDifference.py
DateTimeTools/UnixTime.py
DateTimeTools/UnixTimetoDate.py
DateTimeTools/WithinTimeRange.py
DateTimeTools/_CFunctions.py
DateTimeTools/_CTConv.py
DateTimeTools/_CppLib.py
DateTimeTools/__init__.py
DateTimeTools/_wheelstub.cpython-314-darwin.so
DateTimeTools/__data/__init__.py
DateTimeTools/__data/datetime/lib/libdatetime.1.1.0.dylib
DateTimeTools/__data/datetime/lib/libdatetime.1.dylib
DateTimeTools/__data/datetime/lib/libdatetime.dylib
datetimetools-1.3.1.dist-info/licenses/LICENSE
datetimetools-1.3.1.dist-info/METADATA
datetimetools-1.3.1.dist-info/WHEEL
datetimetools-1.3.1.dist-info/top_level.txt
datetimetools-1.3.1.dist-info/RECORD
