Metadata-Version: 2.4
Name: DateTimeTools
Version: 1.3.1
Summary: A package containing some simple tools to manage dates and times.
Home-page: https://github.com/mattkjames7/DateTimeTools
Author: Matthew Knight James
Author-email: mattkjames7@gmail.com
Classifier: Programming Language :: Python :: 3
Classifier: License :: OSI Approved :: MIT License
Classifier: Operating System :: OS Independent
License-File: LICENSE
Requires-Dist: numpy
Requires-Dist: scipy
Requires-Dist: cdflib
Dynamic: author
Dynamic: author-email
Dynamic: classifier
Dynamic: description
Dynamic: description-content-type
Dynamic: home-page
Dynamic: license-file
Dynamic: requires-dist
Dynamic: summary
